system_monitor/__init__.py
system_monitor/system_monitor.py
system_monitor_cli-0.1.1.dist-info/LICENSE
system_monitor_cli-0.1.1.dist-info/METADATA
system_monitor_cli-0.1.1.dist-info/WHEEL
system_monitor_cli-0.1.1.dist-info/entry_points.txt
system_monitor_cli-0.1.1.dist-info/top_level.txt
system_monitor_cli-0.1.1.dist-info/RECORD
